git_rewrite/__init__.py
git_rewrite/__main__.py
git_rewrite/argbuilder.py
git_rewrite/cli.py
git_rewrite/py.typed
git_rewrite/version.py
git_rewrite/common/__init__.py
git_rewrite/common/config.py
git_rewrite/common/repo.py
git_rewrite/common/stream.py
git_rewrite/compose/__init__.py
git_rewrite/compose/run.py
git_rewrite/flatten/__init__.py
git_rewrite/flatten/rewriter.py
git_rewrite/flatten/run.py
git_rewrite/flatten/tree.py
git_rewrite/remap/__init__.py
git_rewrite/remap/remapper.py
git_rewrite/remap/run.py
git_rewrite/sanitise/__init__.py
git_rewrite/sanitise/config.py
git_rewrite/sanitise/patterns.py
git_rewrite/sanitise/rewriter.py
git_rewrite/sanitise/run.py
git_rewrite/scan/__init__.py
git_rewrite/scan/run.py
git_rewrite/scan/scanner.py
git_rewrite-0.5.0.dist-info/METADATA
git_rewrite-0.5.0.dist-info/WHEEL
git_rewrite-0.5.0.dist-info/entry_points.txt
git_rewrite-0.5.0.dist-info/licenses/LICENSE
git_rewrite-0.5.0.dist-info/RECORD
