Metadata-Version: 2.4
Name: git-rewrite
Version: 0.5.0
Summary: Git history rewriting tools - sanitise, flatten submodules, and remap references
Project-URL: Repository, https://gitlab.com/cyberassessmentlabs/public/tools/git-rewrite
Project-URL: Documentation, https://cyberassessmentlabs.gitlab.io/public/docs/git-rewrite/latest
Author: Cyber Assessment Labs
License-Expression: MIT
License-File: LICENSE
Keywords: git,history,rewrite,sanitise,submodules
Classifier: Development Status :: 4 - Beta
Classifier: Environment :: Console
Classifier: Intended Audience :: Developers
Classifier: License :: OSI Approved :: MIT License
Classifier: Operating System :: OS Independent
Classifier: Programming Language :: Python :: 3
Classifier: Programming Language :: Python :: 3.14
Classifier: Topic :: Software Development :: Version Control :: Git
Requires-Python: >=3.14
